pytermgame/__init__.py
pytermgame/_active.py
pytermgame/_dev.py
pytermgame/_get_key.py
pytermgame/_key_posix.py
pytermgame/_key_win.py
pytermgame/clock.py
pytermgame/collidable.py
pytermgame/coords.py
pytermgame/cursor.py
pytermgame/debugger.py
pytermgame/event.py
pytermgame/game.py
pytermgame/group.py
pytermgame/key.py
pytermgame/profiler.py
pytermgame/scene.py
pytermgame/sprite.py
pytermgame/sprites.py
pytermgame/style.py
pytermgame/surface.py
pytermgame/terminal.py
pytermgame/ui.py
pytermgame-1.2.dist-info/LICENSE
pytermgame-1.2.dist-info/METADATA
pytermgame-1.2.dist-info/WHEEL
pytermgame-1.2.dist-info/top_level.txt
pytermgame-1.2.dist-info/RECORD
