Metadata-Version: 2.1
Name: pytermgame
Version: 1.2
Summary: Like pygame, but in the terminal
License: GNU GENERAL PUBLIC LICENSE
Project-URL: Homepage, https://github.com/tovicheung/pytermgame
Classifier: License :: OSI Approved :: MIT License
Classifier: Programming Language :: Python
Classifier: Programming Language :: Python :: 3
License-File: LICENSE
